rapid_response_xblock/__init__.py
rapid_response_xblock/apps.py
rapid_response_xblock/block.py
rapid_response_xblock/logger.py
rapid_response_xblock/models.py
rapid_response_xblock/utils.py
rapid_response_xblock/migrations/0001_initial.py
rapid_response_xblock/migrations/0002_block_status.py
rapid_response_xblock/migrations/0003_rename_fields.py
rapid_response_xblock/migrations/0004_run.py
rapid_response_xblock/migrations/0005_remove_run_name.py
rapid_response_xblock/migrations/__init__.py
rapid_response_xblock/settings/cms_settings.py
rapid_response_xblock/settings/common.py
rapid_response_xblock/static/css/rapid.css
rapid_response_xblock/static/html/rapid.html
rapid_response_xblock/static/html/rapid_studio.html
rapid_response_xblock/static/js/lib/d3.v4.min.js
rapid_response_xblock/static/js/src_js/rapid.js
rapid_response_xblock/static/js/src_js/rapid_studio.js
rapid_response_xblock-0.11.0.dist-info/METADATA
rapid_response_xblock-0.11.0.dist-info/WHEEL
rapid_response_xblock-0.11.0.dist-info/entry_points.txt
rapid_response_xblock-0.11.0.dist-info/RECORD
