Metadata-Version: 2.4
Name: rapid-response-xblock
Version: 0.11.0
Summary: An Open edX plugin to add rapid response aside for problem xBlocks
Author: MIT Office of Digital Learning
License-Expression: BSD-3-Clause
Keywords: Python,edx
Requires-Python: >=3.11
Requires-Dist: django>=4.0
Requires-Dist: djangorestframework>=3.14.0
Requires-Dist: xblock
